uccl/__init__.py
uccl/collective.py
uccl/p2p.cpython-310-x86_64-linux-gnu.so
uccl/lib/libnccl-efa.so
uccl/lib/libnccl-net-efa.so
uccl/lib/libnccl-net-uccl.so
uccl.libs/libefa-21e848e1.so.1.3.52.0
uccl.libs/libgflags-f3c7dc50.so.2.2.2
uccl.libs/libglog-c040a6f3.so.0.4.0
uccl.libs/liblzma-493cb401.so.5.2.5
uccl.libs/libunwind-5d1f6f10.so.8.0.1
uccl-0.0.1.post4.dist-info/METADATA
uccl-0.0.1.post4.dist-info/WHEEL
uccl-0.0.1.post4.dist-info/top_level.txt
uccl-0.0.1.post4.dist-info/RECORD
uccl-0.0.1.post4.dist-info/licenses/LICENSE
