Metadata-Version: 2.4
Name: uccl
Version: 0.0.1.post4
Summary: UCCL: Ultra and Unified CCL
Home-page: https://github.com/uccl-project/uccl
Author: UCCL Team
License: Apache-2.0
Classifier: Programming Language :: Python :: 3
Requires-Python: >=3.8
License-File: LICENSE
Provides-Extra: cuda
Provides-Extra: rocm
Dynamic: author
Dynamic: classifier
Dynamic: description
Dynamic: description-content-type
Dynamic: home-page
Dynamic: license
Dynamic: license-file
Dynamic: provides-extra
Dynamic: requires-python
Dynamic: summary
